dbm.py
setup.py
micropython_dbm.egg-info/PKG-INFO
micropython_dbm.egg-info/SOURCES.txt
micropython_dbm.egg-info/dependency_links.txt
micropython_dbm.egg-info/top_level.txt